README
ez_setup.py
setup.cfg
setup.py
oe_bakery.egg-info/PKG-INFO
oe_bakery.egg-info/SOURCES.txt
oe_bakery.egg-info/dependency_links.txt
oe_bakery.egg-info/entry_points.txt
oe_bakery.egg-info/not-zip-safe
oe_bakery.egg-info/top_level.txt
oebakery/__init__.py
oebakery/cmd_bake.py
oebakery/cmd_clone.py
oebakery/cmd_config.py
oebakery/cmd_ingredient.py
oebakery/cmd_init.py
oebakery/cmd_prebake.py
oebakery/cmd_pull.py
oebakery/cmd_tmp.py
oebakery/cmd_update.py
oebakery/misc.py
oebakery/oe.py
oebakery/sync.py