Metadata-Version: 1.0
Name: oe-bakery
Version: 0.16.4
Summary: OE-Bakery - OpenEmbedded Development Environment Tool
Home-page: http://dev.doredevelopment.dk/wiki/OpenEmbeddedBakery
Author: Esben Haabendal
Author-email: eha@doredevelopment.dk
License: GPL
Platform: UNKNOWN
